Metadata-Version: 1.0
Name: vins-bin-gauss
Version: 0.1
Summary: Binomial and Gaussian Distributions
Home-page: UNKNOWN
Author: M.Vineeth
Author-email: vinscoder1627@gmail.com
License: UNKNOWN
Platform: UNKNOWN
